{
"meta":{"test_sets":[],"test_metrics":[],"learn_metrics":[{"best_value":"Min","name":"RMSE"}],"launch_mode":"Train","parameters":"","iteration_count":400,"learn_sets":["learn"],"name":"experiment"},
"iterations":[
{"learn":[12189.27978],"iteration":0,"passed_time":0.1174689721,"remaining_time":46.87011988},
{"learn":[11596.40011],"iteration":1,"passed_time":0.1426109507,"remaining_time":28.3795792},
{"learn":[11032.47902],"iteration":2,"passed_time":0.167946314,"remaining_time":22.22489555},
{"learn":[10497.4029],"iteration":3,"passed_time":0.1936507416,"remaining_time":19.17142342},
{"learn":[9988.120933],"iteration":4,"passed_time":0.2191112934,"remaining_time":17.30979217},
{"learn":[9504.884428],"iteration":5,"passed_time":0.2439465066,"remaining_time":16.01915394},
{"learn":[9044.349221],"iteration":6,"passed_time":0.2694481883,"remaining_time":15.12759114},
{"learn":[8606.602838],"iteration":7,"passed_time":0.2959830618,"remaining_time":14.50317003},
{"learn":[8190.840559],"iteration":8,"passed_time":0.3182010256,"remaining_time":13.82406678},
{"learn":[7795.364705],"iteration":9,"passed_time":0.340927544,"remaining_time":13.29617422},
{"learn":[7419.219992],"iteration":10,"passed_time":0.3628291015,"remaining_time":12.83095641},
{"learn":[7061.777953],"iteration":11,"passed_time":0.3853541336,"remaining_time":12.45978365},
{"learn":[6722.271945],"iteration":12,"passed_time":0.4082606361,"remaining_time":12.15360509},
{"learn":[6397.103106],"iteration":13,"passed_time":0.429808681,"remaining_time":11.85043935},
{"learn":[6089.042871],"iteration":14,"passed_time":0.4511641397,"remaining_time":11.57987958},
{"learn":[5797.100452],"iteration":15,"passed_time":0.4716194103,"remaining_time":11.31886585},
{"learn":[5519.785227],"iteration":16,"passed_time":0.4920183673,"remaining_time":11.08488439},
{"learn":[5255.860837],"iteration":17,"passed_time":0.5151695889,"remaining_time":10.9330435},
{"learn":[5003.105071],"iteration":18,"passed_time":0.5381999625,"remaining_time":10.79232556},
{"learn":[4763.384685],"iteration":19,"passed_time":0.5600291475,"remaining_time":10.6405538},
{"learn":[4535.813745],"iteration":20,"passed_time":0.5828614035,"remaining_time":10.51926057},
{"learn":[4319.367115],"iteration":21,"passed_time":0.6047695062,"remaining_time":10.3910397},
{"learn":[4113.303305],"iteration":22,"passed_time":0.628486227,"remaining_time":10.30170903},
{"learn":[3918.202142],"iteration":23,"passed_time":0.6510608993,"remaining_time":10.19995409},
{"learn":[3732.001422],"iteration":24,"passed_time":0.6721409692,"remaining_time":10.08211454},
{"learn":[3554.625909],"iteration":25,"passed_time":0.6938006799,"remaining_time":9.980055934},
{"learn":[3386.536655],"iteration":26,"passed_time":0.7173269241,"remaining_time":9.909738618},
{"learn":[3226.729891],"iteration":27,"passed_time":0.7404260451,"remaining_time":9.837088885},
{"learn":[3074.640467],"iteration":28,"passed_time":0.7629961212,"remaining_time":9.761088309},
{"learn":[2930.488637],"iteration":29,"passed_time":0.7857276599,"remaining_time":9.690641139},
{"learn":[2793.3645],"iteration":30,"passed_time":0.8097033043,"remaining_time":9.638081267},
{"learn":[2662.637749],"iteration":31,"passed_time":0.8312323024,"remaining_time":9.559171478},
{"learn":[2538.692969],"iteration":32,"passed_time":0.8536164346,"remaining_time":9.493249439},
{"learn":[2420.901038],"iteration":33,"passed_time":0.8761581631,"remaining_time":9.431584932},
{"learn":[2308.728893],"iteration":34,"passed_time":0.8993953284,"remaining_time":9.379408425},
{"learn":[2201.55236],"iteration":35,"passed_time":0.919337097,"remaining_time":9.295519537},
{"learn":[2100.644273],"iteration":36,"passed_time":0.9409095882,"remaining_time":9.23108596},
{"learn":[2003.389474],"iteration":37,"passed_time":0.9608224595,"remaining_time":9.153098167},
{"learn":[1912.248717],"iteration":38,"passed_time":0.9821465415,"remaining_time":9.09115132},
{"learn":[1825.131098],"iteration":39,"passed_time":1.001707922,"remaining_time":9.015371298},
{"learn":[1742.476042],"iteration":40,"passed_time":1.021736642,"remaining_time":8.946425721},
{"learn":[1664.1726],"iteration":41,"passed_time":1.04207049,"remaining_time":8.882410367},
{"learn":[1589.854576],"iteration":42,"passed_time":1.062542291,"remaining_time":8.821572048},
{"learn":[1519.529842],"iteration":43,"passed_time":1.084081652,"remaining_time":8.771206095},
{"learn":[1452.104401],"iteration":44,"passed_time":1.104841182,"remaining_time":8.715969322},
{"learn":[1388.558857],"iteration":45,"passed_time":1.126076974,"remaining_time":8.665896713},
{"learn":[1328.698879],"iteration":46,"passed_time":1.148431721,"remaining_time":8.625455264},
{"learn":[1271.639103],"iteration":47,"passed_time":1.170038199,"remaining_time":8.580280122},
{"learn":[1217.846029],"iteration":48,"passed_time":1.199501074,"remaining_time":8.592344426},
{"learn":[1166.596452],"iteration":49,"passed_time":1.221065347,"remaining_time":8.547457426},
{"learn":[1117.999108],"iteration":50,"passed_time":1.244693881,"remaining_time":8.517611069},
{"learn":[1071.897963],"iteration":51,"passed_time":1.266840434,"remaining_time":8.478085979},
{"learn":[1028.365246],"iteration":52,"passed_time":1.288122867,"remaining_time":8.433559148},
{"learn":[987.4578939],"iteration":53,"passed_time":1.308883464,"remaining_time":8.386549605},
{"learn":[948.5047959],"iteration":54,"passed_time":1.329448188,"remaining_time":8.339265908},
{"learn":[912.1413311],"iteration":55,"passed_time":1.349030461,"remaining_time":8.286901405},
{"learn":[877.6070824],"iteration":56,"passed_time":1.369135355,"remaining_time":8.238832046},
{"learn":[844.808097],"iteration":57,"passed_time":1.389098669,"remaining_time":8.190892154},
{"learn":[813.7654109],"iteration":58,"passed_time":1.408377807,"remaining_time":8.139946311},
{"learn":[784.5300738],"iteration":59,"passed_time":1.428308265,"remaining_time":8.093746836},
{"learn":[757.1517251],"iteration":60,"passed_time":1.449376344,"remaining_time":8.054730832},
{"learn":[731.1921813],"iteration":61,"passed_time":1.469574945,"remaining_time":8.011553733},
{"learn":[707.0142793],"iteration":62,"passed_time":1.492350681,"remaining_time":7.982891736},
{"learn":[683.9227485],"iteration":63,"passed_time":1.513066391,"remaining_time":7.943598555},
{"learn":[662.6022903],"iteration":64,"passed_time":1.535966205,"remaining_time":7.916133519},
{"learn":[642.3089295],"iteration":65,"passed_time":1.557832224,"remaining_time":7.883575195},
{"learn":[623.4744597],"iteration":66,"passed_time":1.579809781,"remaining_time":7.851890406},
{"learn":[605.6426362],"iteration":67,"passed_time":1.600436821,"remaining_time":7.813897421},
{"learn":[588.8971374],"iteration":68,"passed_time":1.62237852,"remaining_time":7.782714348},
{"learn":[573.0876833],"iteration":69,"passed_time":1.642482594,"remaining_time":7.743132227},
{"learn":[558.2455731],"iteration":70,"passed_time":1.664027753,"remaining_time":7.710776491},
{"learn":[544.4700653],"iteration":71,"passed_time":1.685361892,"remaining_time":7.677759731},
{"learn":[531.5838523],"iteration":72,"passed_time":1.706688358,"remaining_time":7.645028674},
{"learn":[519.4957171],"iteration":73,"passed_time":1.727209718,"remaining_time":7.609059029},
{"learn":[508.2562597],"iteration":74,"passed_time":1.746216114,"remaining_time":7.566936496},
{"learn":[497.6114758],"iteration":75,"passed_time":1.768040327,"remaining_time":7.537435078},
{"learn":[487.6598595],"iteration":76,"passed_time":1.790573331,"remaining_time":7.511106309},
{"learn":[478.421976],"iteration":77,"passed_time":1.814243548,"remaining_time":7.48956952},
{"learn":[469.7912878],"iteration":78,"passed_time":1.836085019,"remaining_time":7.460547989},
{"learn":[461.7311474],"iteration":79,"passed_time":1.859342299,"remaining_time":7.437369197},
{"learn":[454.1657502],"iteration":80,"passed_time":1.880611031,"remaining_time":7.406357023},
{"learn":[447.1990586],"iteration":81,"passed_time":1.903221766,"remaining_time":7.380786848},
{"learn":[440.7897956],"iteration":82,"passed_time":1.924098284,"remaining_time":7.348664532},
{"learn":[434.669861],"iteration":83,"passed_time":1.943690232,"remaining_time":7.31197754},
{"learn":[429.0696694],"iteration":84,"passed_time":1.966141636,"remaining_time":7.286289592},
{"learn":[423.7836563],"iteration":85,"passed_time":1.988941353,"remaining_time":7.261948663},
{"learn":[418.8843881],"iteration":86,"passed_time":2.010527536,"remaining_time":7.233277227},
{"learn":[414.3719],"iteration":87,"passed_time":2.032431811,"remaining_time":7.205894601},
{"learn":[410.1317835],"iteration":88,"passed_time":2.054039711,"remaining_time":7.17759944},
{"learn":[406.174554],"iteration":89,"passed_time":2.076649926,"remaining_time":7.1529053},
{"learn":[402.6122892],"iteration":90,"passed_time":2.099833462,"remaining_time":7.130203735},
{"learn":[399.1924185],"iteration":91,"passed_time":2.122014417,"remaining_time":7.104135221},
{"learn":[396.0144261],"iteration":92,"passed_time":2.144327483,"remaining_time":7.078586421},
{"learn":[393.1092466],"iteration":93,"passed_time":2.167461047,"remaining_time":7.05577745},
{"learn":[390.3314598],"iteration":94,"passed_time":2.187569082,"remaining_time":7.023248105},
{"learn":[387.7985074],"iteration":95,"passed_time":2.209456824,"remaining_time":6.996613275},
{"learn":[385.4087075],"iteration":96,"passed_time":2.232198491,"remaining_time":6.97274374},
{"learn":[383.2417293],"iteration":97,"passed_time":2.254664679,"remaining_time":6.948048298},
{"learn":[381.1885876],"iteration":98,"passed_time":2.275226703,"remaining_time":6.91760846},
{"learn":[379.3254256],"iteration":99,"passed_time":2.297463751,"remaining_time":6.892391253},
{"learn":[377.4480298],"iteration":100,"passed_time":2.319374932,"remaining_time":6.866268364},
{"learn":[375.7909633],"iteration":101,"passed_time":2.340282039,"remaining_time":6.837294584},
{"learn":[374.1173353],"iteration":102,"passed_time":2.363312879,"remaining_time":6.814601215},
{"learn":[372.6293346],"iteration":103,"passed_time":2.383848545,"remaining_time":6.784799705},
{"learn":[371.310072],"iteration":104,"passed_time":2.403699941,"remaining_time":6.753252216},
{"learn":[370.0576381],"iteration":105,"passed_time":2.42623108,"remaining_time":6.729357901},
{"learn":[368.8106974],"iteration":106,"passed_time":2.44760522,"remaining_time":6.702320836},
{"learn":[367.413037],"iteration":107,"passed_time":2.469988128,"remaining_time":6.67811605},
{"learn":[366.1192928],"iteration":108,"passed_time":2.493023235,"remaining_time":6.655685884},
{"learn":[365.1256544],"iteration":109,"passed_time":2.515744869,"remaining_time":6.63241829},
{"learn":[364.1261345],"iteration":110,"passed_time":2.537005983,"remaining_time":6.605357919},
{"learn":[363.0112302],"iteration":111,"passed_time":2.559513737,"remaining_time":6.581606752},
{"learn":[361.8637725],"iteration":112,"passed_time":2.582331486,"remaining_time":6.558664924},
{"learn":[361.0428188],"iteration":113,"passed_time":2.60525823,"remaining_time":6.535998716},
{"learn":[360.265337],"iteration":114,"passed_time":2.62543475,"remaining_time":6.506512205},
{"learn":[359.5122742],"iteration":115,"passed_time":2.645108625,"remaining_time":6.4759556},
{"learn":[358.796724],"iteration":116,"passed_time":2.66411227,"remaining_time":6.443963867},
{"learn":[358.1589514],"iteration":117,"passed_time":2.684638869,"remaining_time":6.415831874},
{"learn":[357.5155066],"iteration":118,"passed_time":2.703701516,"remaining_time":6.384370808},
{"learn":[356.697216],"iteration":119,"passed_time":2.723566131,"remaining_time":6.354987638},
{"learn":[356.122113],"iteration":120,"passed_time":2.744050152,"remaining_time":6.327190021},
{"learn":[355.5987496],"iteration":121,"passed_time":2.76574414,"remaining_time":6.302269434},
{"learn":[355.0991871],"iteration":122,"passed_time":2.786804926,"remaining_time":6.275975322},
{"learn":[354.6263143],"iteration":123,"passed_time":2.807359402,"remaining_time":6.248638668},
{"learn":[354.159952],"iteration":124,"passed_time":2.827638937,"remaining_time":6.220805661},
{"learn":[353.4793952],"iteration":125,"passed_time":2.847350866,"remaining_time":6.191858232},
{"learn":[353.0587601],"iteration":126,"passed_time":2.868840638,"remaining_time":6.166877907},
{"learn":[352.6524735],"iteration":127,"passed_time":2.891446635,"remaining_time":6.144324099},
{"learn":[352.1732065],"iteration":128,"passed_time":2.91413599,"remaining_time":6.1219446},
{"learn":[351.6333696],"iteration":129,"passed_time":2.935090323,"remaining_time":6.095956824},
{"learn":[351.2342183],"iteration":130,"passed_time":2.958390974,"remaining_time":6.074863909},
{"learn":[350.8837812],"iteration":131,"passed_time":2.978847836,"remaining_time":6.047963787},
{"learn":[350.3339019],"iteration":132,"passed_time":2.998581099,"remaining_time":6.019707921},
{"learn":[349.962543],"iteration":133,"passed_time":3.017987456,"remaining_time":5.990930323},
{"learn":[349.5965314],"iteration":134,"passed_time":3.040581241,"remaining_time":5.968548361},
{"learn":[349.1486481],"iteration":135,"passed_time":3.061867497,"remaining_time":5.943625142},
{"learn":[348.6856091],"iteration":136,"passed_time":3.081331575,"remaining_time":5.915256965},
{"learn":[348.3406853],"iteration":137,"passed_time":3.100787316,"remaining_time":5.887002006},
{"learn":[348.0299055],"iteration":138,"passed_time":3.119972862,"remaining_time":5.858366308},
{"learn":[347.6779475],"iteration":139,"passed_time":3.140335275,"remaining_time":5.832051225},
{"learn":[347.34115],"iteration":140,"passed_time":3.162515385,"remaining_time":5.809159466},
{"learn":[347.0720172],"iteration":141,"passed_time":3.183866465,"remaining_time":5.784771465},
{"learn":[346.637596],"iteration":142,"passed_time":3.206669971,"remaining_time":5.763036242},
{"learn":[346.3744224],"iteration":143,"passed_time":3.228853596,"remaining_time":5.740184171},
{"learn":[346.0389562],"iteration":144,"passed_time":3.250199486,"remaining_time":5.715868061},
{"learn":[345.7883856],"iteration":145,"passed_time":3.271121944,"remaining_time":5.690855985},
{"learn":[345.4721774],"iteration":146,"passed_time":3.290717032,"remaining_time":5.663615027},
{"learn":[345.2503287],"iteration":147,"passed_time":3.310949131,"remaining_time":5.637562034},
{"learn":[344.9684316],"iteration":148,"passed_time":3.33050419,"remaining_time":5.610446655},
{"learn":[344.6553252],"iteration":149,"passed_time":3.350218237,"remaining_time":5.583697062},
{"learn":[344.2351386],"iteration":150,"passed_time":3.371128814,"remaining_time":5.559013739},
{"learn":[343.9346787],"iteration":151,"passed_time":3.391149878,"remaining_time":5.532928749},
{"learn":[343.7153566],"iteration":152,"passed_time":3.410645453,"remaining_time":5.506074686},
{"learn":[343.362758],"iteration":153,"passed_time":3.432164726,"remaining_time":5.482548848},
{"learn":[343.0728033],"iteration":154,"passed_time":3.455745163,"remaining_time":5.462306871},
{"learn":[342.8863116],"iteration":155,"passed_time":3.480450753,"remaining_time":5.443781946},
{"learn":[342.5831698],"iteration":156,"passed_time":3.503571539,"remaining_time":5.422725376},
{"learn":[342.3634652],"iteration":157,"passed_time":3.525648958,"remaining_time":5.400044607},
{"learn":[342.1005515],"iteration":158,"passed_time":3.545623503,"remaining_time":5.374184052},
{"learn":[341.8875254],"iteration":159,"passed_time":3.566521025,"remaining_time":5.349781538},
{"learn":[341.6996912],"iteration":160,"passed_time":3.587255151,"remaining_time":5.325180007},
{"learn":[341.4885774],"iteration":161,"passed_time":3.608206573,"remaining_time":5.30094546},
{"learn":[341.2101643],"iteration":162,"passed_time":3.627276655,"remaining_time":5.27401575},
{"learn":[340.9204204],"iteration":163,"passed_time":3.646362907,"remaining_time":5.247205158},
{"learn":[340.6729115],"iteration":164,"passed_time":3.665253591,"remaining_time":5.220209659},
{"learn":[340.4707215],"iteration":165,"passed_time":3.687747944,"remaining_time":5.19839168},
{"learn":[340.229933],"iteration":166,"passed_time":3.70824819,"remaining_time":5.173783403},
{"learn":[339.9211389],"iteration":167,"passed_time":3.727867237,"remaining_time":5.148007137},
{"learn":[339.7918849],"iteration":168,"passed_time":3.749000068,"remaining_time":5.124372874},
{"learn":[339.6678918],"iteration":169,"passed_time":3.769821667,"remaining_time":5.100346961},
{"learn":[339.4578772],"iteration":170,"passed_time":3.790741671,"remaining_time":5.076490309},
{"learn":[339.242954],"iteration":171,"passed_time":3.810468762,"remaining_time":5.051086499},
{"learn":[339.1040556],"iteration":172,"passed_time":3.828528379,"remaining_time":5.023560359},
{"learn":[338.7752324],"iteration":173,"passed_time":3.847593093,"remaining_time":4.9974485},
{"learn":[338.5707183],"iteration":174,"passed_time":3.868420745,"remaining_time":4.973683815},
{"learn":[338.3451095],"iteration":175,"passed_time":3.889646383,"remaining_time":4.950459033},
{"learn":[338.1441255],"iteration":176,"passed_time":3.911072897,"remaining_time":4.927509921},
{"learn":[337.7780601],"iteration":177,"passed_time":3.933424648,"remaining_time":4.905731864},
{"learn":[337.4199615],"iteration":178,"passed_time":3.953581573,"remaining_time":4.881237585},
{"learn":[337.2343581],"iteration":179,"passed_time":3.973201881,"remaining_time":4.856135632},
{"learn":[336.9922143],"iteration":180,"passed_time":3.992399817,"remaining_time":4.830583204},
{"learn":[336.817841],"iteration":181,"passed_time":4.013680797,"remaining_time":4.80759568},
{"learn":[336.6641268],"iteration":182,"passed_time":4.037438668,"remaining_time":4.787563885},
{"learn":[336.4803262],"iteration":183,"passed_time":4.060089358,"remaining_time":4.766191855},
{"learn":[336.2900902],"iteration":184,"passed_time":4.082143775,"remaining_time":4.744113035},
{"learn":[336.0607026],"iteration":185,"passed_time":4.103260542,"remaining_time":4.720955677},
{"learn":[335.94463],"iteration":186,"passed_time":4.124567778,"remaining_time":4.698037094},
{"learn":[335.7826928],"iteration":187,"passed_time":4.145143463,"remaining_time":4.674310714},
{"learn":[335.567553],"iteration":188,"passed_time":4.164905924,"remaining_time":4.649709788},
{"learn":[335.2857675],"iteration":189,"passed_time":4.184644594,"remaining_time":4.625133499},
{"learn":[335.0250518],"iteration":190,"passed_time":4.205225121,"remaining_time":4.601529059},
{"learn":[334.8955049],"iteration":191,"passed_time":4.224317991,"remaining_time":4.576344491},
{"learn":[334.7018449],"iteration":192,"passed_time":4.24401774,"remaining_time":4.551873949},
{"learn":[334.5155072],"iteration":193,"passed_time":4.265801334,"remaining_time":4.529665334},
{"learn":[334.2875806],"iteration":194,"passed_time":4.285706327,"remaining_time":4.505486139},
{"learn":[334.0983952],"iteration":195,"passed_time":4.30670701,"remaining_time":4.48249097},
{"learn":[333.8586293],"iteration":196,"passed_time":4.328286628,"remaining_time":4.460112616},
{"learn":[333.6826821],"iteration":197,"passed_time":4.349936019,"remaining_time":4.437813515},
{"learn":[333.5148241],"iteration":198,"passed_time":4.37296841,"remaining_time":4.416917841},
{"learn":[333.3139069],"iteration":199,"passed_time":4.398424764,"remaining_time":4.398424764},
{"learn":[333.0935287],"iteration":200,"passed_time":4.421314662,"remaining_time":4.377321481},
{"learn":[332.8102605],"iteration":201,"passed_time":4.443064567,"remaining_time":4.355083091},
{"learn":[332.5447199],"iteration":202,"passed_time":4.46465668,"remaining_time":4.332696384},
{"learn":[332.422977],"iteration":203,"passed_time":4.486396374,"remaining_time":4.310459261},
{"learn":[332.1460749],"iteration":204,"passed_time":4.508225766,"remaining_time":4.288312314},
{"learn":[331.9878072],"iteration":205,"passed_time":4.52956529,"remaining_time":4.265707118},
{"learn":[331.6544109],"iteration":206,"passed_time":4.549933727,"remaining_time":4.24220874},
{"learn":[331.5051642],"iteration":207,"passed_time":4.5727109,"remaining_time":4.220963908},
{"learn":[331.3174129],"iteration":208,"passed_time":4.593431575,"remaining_time":4.197825028},
{"learn":[331.159108],"iteration":209,"passed_time":4.614952542,"remaining_time":4.175433252},
{"learn":[330.9181743],"iteration":210,"passed_time":4.638716009,"remaining_time":4.155058416},
{"learn":[330.7514538],"iteration":211,"passed_time":4.661496464,"remaining_time":4.133779883},
{"learn":[330.6084744],"iteration":212,"passed_time":4.683730642,"remaining_time":4.112007653},
{"learn":[330.3758228],"iteration":213,"passed_time":4.706582772,"remaining_time":4.090768203},
{"learn":[330.0872397],"iteration":214,"passed_time":4.726651538,"remaining_time":4.067118765},
{"learn":[329.9043158],"iteration":215,"passed_time":4.746991948,"remaining_time":4.043733882},
{"learn":[329.7744174],"iteration":216,"passed_time":4.76831937,"remaining_time":4.021209422},
{"learn":[329.4442044],"iteration":217,"passed_time":4.787599926,"remaining_time":3.996987094},
{"learn":[329.301972],"iteration":218,"passed_time":4.809426698,"remaining_time":3.974914303},
{"learn":[329.1069935],"iteration":219,"passed_time":4.832376294,"remaining_time":3.953762422},
{"learn":[328.7663903],"iteration":220,"passed_time":4.854422631,"remaining_time":3.931862674},
{"learn":[328.5760538],"iteration":221,"passed_time":4.875351759,"remaining_time":3.909065825},
{"learn":[328.4312099],"iteration":222,"passed_time":4.899320951,"remaining_time":3.888698692},
{"learn":[328.2722113],"iteration":223,"passed_time":4.921101038,"remaining_time":3.866579387},
{"learn":[328.0483686],"iteration":224,"passed_time":4.943452135,"remaining_time":3.844907216},
{"learn":[327.7256882],"iteration":225,"passed_time":4.963560771,"remaining_time":3.82150254},
{"learn":[327.5310671],"iteration":226,"passed_time":4.985406943,"remaining_time":3.799451106},
{"learn":[327.4143166],"iteration":227,"passed_time":5.006501781,"remaining_time":3.776834677},
{"learn":[327.2332575],"iteration":228,"passed_time":5.029370261,"remaining_time":3.755555959},
{"learn":[327.1039461],"iteration":229,"passed_time":5.05181873,"remaining_time":3.733952974},
{"learn":[326.9182365],"iteration":230,"passed_time":5.071879317,"remaining_time":3.71059569},
{"learn":[326.7414614],"iteration":231,"passed_time":5.091809769,"remaining_time":3.687172591},
{"learn":[326.5153866],"iteration":232,"passed_time":5.11269197,"remaining_time":3.664461626},
{"learn":[326.377521],"iteration":233,"passed_time":5.131447372,"remaining_time":3.640257537},
{"learn":[326.1853611],"iteration":234,"passed_time":5.150894394,"remaining_time":3.616585425},
{"learn":[325.905946],"iteration":235,"passed_time":5.170352974,"remaining_time":3.592957151},
{"learn":[325.8063935],"iteration":236,"passed_time":5.188224903,"remaining_time":3.568272823},
{"learn":[325.6929991],"iteration":237,"passed_time":5.207072404,"remaining_time":3.544309788},
{"learn":[325.5716008],"iteration":238,"passed_time":5.225448732,"remaining_time":3.520072158},
{"learn":[325.4459454],"iteration":239,"passed_time":5.247009818,"remaining_time":3.498006545},
{"learn":[325.2623293],"iteration":240,"passed_time":5.270038416,"remaining_time":3.476913312},
{"learn":[325.1183587],"iteration":241,"passed_time":5.292806505,"remaining_time":3.455633999},
{"learn":[324.9796655],"iteration":242,"passed_time":5.315515159,"remaining_time":3.434304033},
{"learn":[324.8623639],"iteration":243,"passed_time":5.336691156,"remaining_time":3.411982871},
{"learn":[324.6189399],"iteration":244,"passed_time":5.356565102,"remaining_time":3.388847309},
{"learn":[324.4995201],"iteration":245,"passed_time":5.376801618,"remaining_time":3.36596524},
{"learn":[324.2628649],"iteration":246,"passed_time":5.399634832,"remaining_time":3.344713074},
{"learn":[324.0858724],"iteration":247,"passed_time":5.422121284,"remaining_time":3.323235626},
{"learn":[323.9382479],"iteration":248,"passed_time":5.444530432,"remaining_time":3.301703194},
{"learn":[323.7829411],"iteration":249,"passed_time":5.468185196,"remaining_time":3.280911117},
{"learn":[323.6246223],"iteration":250,"passed_time":5.490721156,"remaining_time":3.25943208},
{"learn":[323.4660162],"iteration":251,"passed_time":5.512527143,"remaining_time":3.237515941},
{"learn":[323.2600873],"iteration":252,"passed_time":5.532811165,"remaining_time":3.214716369},
{"learn":[323.0557612],"iteration":253,"passed_time":5.555146018,"remaining_time":3.193115428},
{"learn":[322.9014099],"iteration":254,"passed_time":5.574831193,"remaining_time":3.170002051},
{"learn":[322.7816701],"iteration":255,"passed_time":5.596025527,"remaining_time":3.147764359},
{"learn":[322.629608],"iteration":256,"passed_time":5.617826451,"remaining_time":3.125872306},
{"learn":[322.5253601],"iteration":257,"passed_time":5.63847957,"remaining_time":3.103349221},
{"learn":[322.3530614],"iteration":258,"passed_time":5.658797116,"remaining_time":3.08065789},
{"learn":[322.2063289],"iteration":259,"passed_time":5.679702815,"remaining_time":3.058301516},
{"learn":[322.120086],"iteration":260,"passed_time":5.698976148,"remaining_time":3.035086914},
{"learn":[322.0173995],"iteration":261,"passed_time":5.719365169,"remaining_time":3.012490051},
{"learn":[321.9150231],"iteration":262,"passed_time":5.742277451,"remaining_time":2.991224376},
{"learn":[321.7633296],"iteration":263,"passed_time":5.766508305,"remaining_time":2.97062549},
{"learn":[321.5523245],"iteration":264,"passed_time":5.790458285,"remaining_time":2.949856108},
{"learn":[321.4310524],"iteration":265,"passed_time":5.812852987,"remaining_time":2.928279324},
{"learn":[321.2857349],"iteration":266,"passed_time":5.835643891,"remaining_time":2.906893773},
{"learn":[321.1756333],"iteration":267,"passed_time":5.85505001,"remaining_time":2.883830602},
{"learn":[321.0656658],"iteration":268,"passed_time":5.876330257,"remaining_time":2.8617073},
{"learn":[320.9037451],"iteration":269,"passed_time":5.896419143,"remaining_time":2.839016624},
{"learn":[320.7678734],"iteration":270,"passed_time":5.915500408,"remaining_time":2.815865508},
{"learn":[320.5966422],"iteration":271,"passed_time":5.935519625,"remaining_time":2.793185706},
{"learn":[320.4211343],"iteration":272,"passed_time":5.955868531,"remaining_time":2.770678767},
{"learn":[320.1818889],"iteration":273,"passed_time":5.987184831,"remaining_time":2.753230981},
{"learn":[320.075372],"iteration":274,"passed_time":6.010098795,"remaining_time":2.731863089},
{"learn":[319.9484732],"iteration":275,"passed_time":6.030366894,"remaining_time":2.709295271},
{"learn":[319.8469206],"iteration":276,"passed_time":6.051060962,"remaining_time":2.686933207},
{"learn":[319.732501],"iteration":277,"passed_time":6.070490606,"remaining_time":2.664028252},
{"learn":[319.6442629],"iteration":278,"passed_time":6.090166776,"remaining_time":2.641255125},
{"learn":[319.5500509],"iteration":279,"passed_time":6.10995987,"remaining_time":2.61855423},
{"learn":[319.3332244],"iteration":280,"passed_time":6.130174326,"remaining_time":2.596052473},
{"learn":[319.2008588],"iteration":281,"passed_time":6.152457563,"remaining_time":2.574432597},
{"learn":[319.0509342],"iteration":282,"passed_time":6.174964731,"remaining_time":2.552900613},
{"learn":[318.9640909],"iteration":283,"passed_time":6.19535631,"remaining_time":2.530497648},
{"learn":[318.7938078],"iteration":284,"passed_time":6.218118872,"remaining_time":2.50906551},
{"learn":[318.6887446],"iteration":285,"passed_time":6.239457805,"remaining_time":2.487056608},
{"learn":[318.5119722],"iteration":286,"passed_time":6.264197141,"remaining_time":2.466391209},
{"learn":[318.4139998],"iteration":287,"passed_time":6.283367605,"remaining_time":2.443531846},
{"learn":[318.1759128],"iteration":288,"passed_time":6.302021704,"remaining_time":2.420499686},
{"learn":[317.9399967],"iteration":289,"passed_time":6.321540498,"remaining_time":2.397825706},
{"learn":[317.8497256],"iteration":290,"passed_time":6.341696722,"remaining_time":2.375412174},
{"learn":[317.6549453],"iteration":291,"passed_time":6.362313885,"remaining_time":2.353184587},
{"learn":[317.5126177],"iteration":292,"passed_time":6.381773281,"remaining_time":2.330545191},
{"learn":[317.3381056],"iteration":293,"passed_time":6.402475993,"remaining_time":2.308375698},
{"learn":[317.1663875],"iteration":294,"passed_time":6.422592412,"remaining_time":2.286007469},
{"learn":[316.9844151],"iteration":295,"passed_time":6.443834031,"remaining_time":2.264049795},
{"learn":[316.8243199],"iteration":296,"passed_time":6.464837144,"remaining_time":2.242014228},
{"learn":[316.6687672],"iteration":297,"passed_time":6.48732242,"remaining_time":2.220492909},
{"learn":[316.5516303],"iteration":298,"passed_time":6.508334409,"remaining_time":2.198467476},
{"learn":[316.4012417],"iteration":299,"passed_time":6.528576311,"remaining_time":2.176192104},
{"learn":[316.3099277],"iteration":300,"passed_time":6.549565947,"remaining_time":2.154176175},
{"learn":[316.142712],"iteration":301,"passed_time":6.568751914,"remaining_time":2.131581747},
{"learn":[316.0232583],"iteration":302,"passed_time":6.588989192,"remaining_time":2.109346375},
{"learn":[315.9040282],"iteration":303,"passed_time":6.609232252,"remaining_time":2.087125974},
{"learn":[315.7690021],"iteration":304,"passed_time":6.628953784,"remaining_time":2.064756097},
{"learn":[315.6206474],"iteration":305,"passed_time":6.650543425,"remaining_time":2.042977392},
{"learn":[315.5164106],"iteration":306,"passed_time":6.672086222,"remaining_time":2.021185728},
{"learn":[315.4201315],"iteration":307,"passed_time":6.69367817,"remaining_time":1.999410363},
{"learn":[315.155855],"iteration":308,"passed_time":6.715190086,"remaining_time":1.977612614},
{"learn":[314.9465003],"iteration":309,"passed_time":6.737793673,"remaining_time":1.956133647},
{"learn":[314.8727444],"iteration":310,"passed_time":6.757813942,"remaining_time":1.93390817},
{"learn":[314.7845193],"iteration":311,"passed_time":6.776471667,"remaining_time":1.911312522},
{"learn":[314.7026075],"iteration":312,"passed_time":6.799150304,"remaining_time":1.889859669},
{"learn":[314.5810151],"iteration":313,"passed_time":6.820900043,"remaining_time":1.868144598},
{"learn":[314.4382004],"iteration":314,"passed_time":6.841864594,"remaining_time":1.84621743},
{"learn":[314.3336795],"iteration":315,"passed_time":6.862486932,"remaining_time":1.824205387},
{"learn":[314.1861329],"iteration":316,"passed_time":6.88418645,"remaining_time":1.802484149},
{"learn":[314.0437872],"iteration":317,"passed_time":6.905750429,"remaining_time":1.780728098},
{"learn":[313.8657509],"iteration":318,"passed_time":6.926825689,"remaining_time":1.758849156},
{"learn":[313.6888852],"iteration":319,"passed_time":6.946634234,"remaining_time":1.736658558},
{"learn":[313.5720697],"iteration":320,"passed_time":6.9655169,"remaining_time":1.714254938},
{"learn":[313.3961351],"iteration":321,"passed_time":6.984396705,"remaining_time":1.691872494},
{"learn":[313.3159598],"iteration":322,"passed_time":7.003074345,"remaining_time":1.669463544},
{"learn":[313.1376858],"iteration":323,"passed_time":7.023248406,"remaining_time":1.647428639},
{"learn":[313.0470602],"iteration":324,"passed_time":7.042978711,"remaining_time":1.625302779},
{"learn":[312.9056747],"iteration":325,"passed_time":7.06548803,"remaining_time":1.603822436},
{"learn":[312.6398836],"iteration":326,"passed_time":7.083271001,"remaining_time":1.581280682},
{"learn":[312.4975806],"iteration":327,"passed_time":7.105075432,"remaining_time":1.559650705},
{"learn":[312.3483786],"iteration":328,"passed_time":7.125864137,"remaining_time":1.537800467},
{"learn":[312.2764009],"iteration":329,"passed_time":7.149680207,"remaining_time":1.516598832},
{"learn":[312.1106683],"iteration":330,"passed_time":7.169829208,"remaining_time":1.494616965},
{"learn":[311.9545473],"iteration":331,"passed_time":7.188575066,"remaining_time":1.472358748},
{"learn":[311.8140411],"iteration":332,"passed_time":7.209666446,"remaining_time":1.450593549},
{"learn":[311.6850042],"iteration":333,"passed_time":7.228923501,"remaining_time":1.428469913},
{"learn":[311.5415431],"iteration":334,"passed_time":7.24857325,"remaining_time":1.406439586},
{"learn":[311.4340469],"iteration":335,"passed_time":7.268860032,"remaining_time":1.384544768},
{"learn":[311.3085196],"iteration":336,"passed_time":7.289714043,"remaining_time":1.362765533},
{"learn":[311.2277929],"iteration":337,"passed_time":7.311797763,"remaining_time":1.341217341},
{"learn":[311.0911055],"iteration":338,"passed_time":7.333013552,"remaining_time":1.319509813},
{"learn":[311.0192871],"iteration":339,"passed_time":7.353657748,"remaining_time":1.297704308},
{"learn":[310.8615806],"iteration":340,"passed_time":7.375121056,"remaining_time":1.276047338},
{"learn":[310.7310419],"iteration":341,"passed_time":7.394883834,"remaining_time":1.254103106},
{"learn":[310.6007217],"iteration":342,"passed_time":7.414918439,"remaining_time":1.232216767},
{"learn":[310.4964945],"iteration":343,"passed_time":7.43588536,"remaining_time":1.210492966},
{"learn":[310.2847482],"iteration":344,"passed_time":7.455297765,"remaining_time":1.188525731},
{"learn":[310.1270513],"iteration":345,"passed_time":7.478488756,"remaining_time":1.167162985},
{"learn":[309.9888928],"iteration":346,"passed_time":7.499932912,"remaining_time":1.145522894},
{"learn":[309.8817345],"iteration":347,"passed_time":7.521525726,"remaining_time":1.123906143},
{"learn":[309.7495499],"iteration":348,"passed_time":7.542408263,"remaining_time":1.102185735},
{"learn":[309.6768311],"iteration":349,"passed_time":7.563186931,"remaining_time":1.080455276},
{"learn":[309.6002847],"iteration":350,"passed_time":7.585502546,"remaining_time":1.0589448},
{"learn":[309.4663205],"iteration":351,"passed_time":7.608357965,"remaining_time":1.037503359},
{"learn":[309.3152996],"iteration":352,"passed_time":7.629006593,"remaining_time":1.015760085},
{"learn":[309.1668954],"iteration":353,"passed_time":7.649500806,"remaining_time":0.9940029296},
{"learn":[309.0888771],"iteration":354,"passed_time":7.668942645,"remaining_time":0.9721194902},
{"learn":[308.9257892],"iteration":355,"passed_time":7.687186285,"remaining_time":0.9501016756},
{"learn":[308.754272],"iteration":356,"passed_time":7.706647195,"remaining_time":0.928251623},
{"learn":[308.6443751],"iteration":357,"passed_time":7.729008892,"remaining_time":0.9067552331},
{"learn":[308.5442047],"iteration":358,"passed_time":7.748104117,"remaining_time":0.8848809716},
{"learn":[308.478961],"iteration":359,"passed_time":7.770249357,"remaining_time":0.8633610397},
{"learn":[308.298771],"iteration":360,"passed_time":7.79135863,"remaining_time":0.8417257246},
{"learn":[308.205566],"iteration":361,"passed_time":7.812705816,"remaining_time":0.82011829},
{"learn":[308.08871],"iteration":362,"passed_time":7.833425651,"remaining_time":0.7984483446},
{"learn":[307.9537989],"iteration":363,"passed_time":7.854196265,"remaining_time":0.7767886415},
{"learn":[307.86967],"iteration":364,"passed_time":7.875260982,"remaining_time":0.755162012},
{"learn":[307.6495774],"iteration":365,"passed_time":7.896661807,"remaining_time":0.733569676},
{"learn":[307.494283],"iteration":366,"passed_time":7.916112955,"remaining_time":0.7118030722},
{"learn":[307.3925505],"iteration":367,"passed_time":7.935786497,"remaining_time":0.690068391},
{"learn":[307.2465741],"iteration":368,"passed_time":7.957310895,"remaining_time":0.6685003733},
{"learn":[307.1334295],"iteration":369,"passed_time":7.977259344,"remaining_time":0.6468048117},
{"learn":[307.0328768],"iteration":370,"passed_time":8.000508524,"remaining_time":0.6253766771},
{"learn":[306.929111],"iteration":371,"passed_time":8.02106915,"remaining_time":0.6037363876},
{"learn":[306.8158355],"iteration":372,"passed_time":8.044076879,"remaining_time":0.5822790234},
{"learn":[306.7403736],"iteration":373,"passed_time":8.066201025,"remaining_time":0.5607519429},
{"learn":[306.6554966],"iteration":374,"passed_time":8.086410986,"remaining_time":0.5390940657},
{"learn":[306.507563],"iteration":375,"passed_time":8.107390887,"remaining_time":0.5174930354},
{"learn":[306.3423944],"iteration":376,"passed_time":8.126349105,"remaining_time":0.4957719613},
{"learn":[306.2027362],"iteration":377,"passed_time":8.146937673,"remaining_time":0.4741603937},
{"learn":[306.0977046],"iteration":378,"passed_time":8.165700203,"remaining_time":0.4524530455},
{"learn":[305.9896136],"iteration":379,"passed_time":8.185104298,"remaining_time":0.4307949631},
{"learn":[305.8803466],"iteration":380,"passed_time":8.204847691,"remaining_time":0.4091656329},
{"learn":[305.7311218],"iteration":381,"passed_time":8.225647829,"remaining_time":0.387595971},
{"learn":[305.6566279],"iteration":382,"passed_time":8.245456948,"remaining_time":0.3659863397},
{"learn":[305.5756857],"iteration":383,"passed_time":8.268287929,"remaining_time":0.344511997},
{"learn":[305.4728142],"iteration":384,"passed_time":8.289162231,"remaining_time":0.3229543726},
{"learn":[305.296313],"iteration":385,"passed_time":8.308954111,"remaining_time":0.3013610299},
{"learn":[305.2299857],"iteration":386,"passed_time":8.331059298,"remaining_time":0.2798547051},
{"learn":[305.0874814],"iteration":387,"passed_time":8.351373458,"remaining_time":0.2582899008},
{"learn":[304.9767919],"iteration":388,"passed_time":8.372016322,"remaining_time":0.2367408214},
{"learn":[304.8763353],"iteration":389,"passed_time":8.392336327,"remaining_time":0.215188111},
{"learn":[304.7401552],"iteration":390,"passed_time":8.414459511,"remaining_time":0.1936832113},
{"learn":[304.6788745],"iteration":391,"passed_time":8.434867498,"remaining_time":0.172140153},
{"learn":[304.6071047],"iteration":392,"passed_time":8.456284165,"remaining_time":0.1506208375},
{"learn":[304.4972441],"iteration":393,"passed_time":8.477560339,"remaining_time":0.1290999036},
{"learn":[304.3645894],"iteration":394,"passed_time":8.500487357,"remaining_time":0.1076011058},
{"learn":[304.2567195],"iteration":395,"passed_time":8.522598079,"remaining_time":0.08608684928},
{"learn":[304.1266252],"iteration":396,"passed_time":8.543857281,"remaining_time":0.06456315326},
{"learn":[303.9980107],"iteration":397,"passed_time":8.565268368,"remaining_time":0.04304154959},
{"learn":[303.9040871],"iteration":398,"passed_time":8.586485556,"remaining_time":0.02152001392},
{"learn":[303.7814834],"iteration":399,"passed_time":8.608039276,"remaining_time":0}
]}